supertime/__init__.py
supertime/function.py
supertime/py.typed
supertime-0.0.1.dist-info/LICENSE
supertime-0.0.1.dist-info/METADATA
supertime-0.0.1.dist-info/WHEEL
supertime-0.0.1.dist-info/top_level.txt
supertime-0.0.1.dist-info/RECORD
